libprime/__init__.py
libprime/prime_number_check.py
libprime-0.0.1b3.dist-info/LICENSE.txt
libprime-0.0.1b3.dist-info/METADATA
libprime-0.0.1b3.dist-info/WHEEL
libprime-0.0.1b3.dist-info/top_level.txt
libprime-0.0.1b3.dist-info/RECORD
