Metadata-Version: 2.1
Name: libprime
Version: 0.0.1b3
Summary: A library to manipulate prime numbers
Home-page: http://pypi.python.org/pypi/libprime
Author: shankar
Author-email: shankar162003@gmail.com
License: LICENSE.txt
Platform: UNKNOWN
Classifier: License :: OSI Approved :: BSD License
Classifier: Framework :: IDLE
Classifier: Development Status :: 2 - Pre-Alpha
Classifier: Environment :: Console
Classifier: Intended Audience :: Developers
Classifier: Natural Language :: English
Classifier: Operating System :: OS Independent
Classifier: Programming Language :: Python :: 3.4
Classifier: Topic :: Security :: Cryptography
